{"stats":{"minecraft:mined":{"minecraft:dark_oak_planks":5,"minecraft:large_amethyst_bud":3,"minecraft:spruce_planks":1,"minecraft:white_bed":3,"minecraft:farmland":12,"minecraft:cobbled_deepslate_stairs":4,"minecraft:cherry_log":14,"minecraft:cobblestone_stairs":1,"minecraft:potted_cactus":2,"minecraft:brewing_stand":3,"minecraft:carved_pumpkin":1,"minecraft:granite":5,"minecraft:grass_block":245,"minecraft:light_gray_bed":1,"minecraft:oak_pressure_plate":12,"minecraft:soul_soil":1,"minecraft:crimson_fungus":1,"minecraft:spawner":2,"minecraft:weeping_vines_plant":16,"minecraft:cobbled_deepslate":107,"minecraft:iron_ore":189,"minecraft:barrel":1,"minecraft:fire":64,"minecraft:pumpkin":71,"minecraft:deepslate_lapis_ore":23,"minecraft:pointed_dripstone":7,"minecraft:dirt_path":3,"minecraft:water_cauldron":3,"minecraft:iron_bars":2,"minecraft:birch_wall_sign":1,"minecraft:end_stone_bricks":4,"minecraft:blue_orchid":33,"minecraft:player_head":10,"minecraft:tripwire":1,"minecraft:deepslate_redstone_ore":29,"minecraft:red_bed":3,"minecraft:blackstone":9,"minecraft:magenta_wall_banner":10,"minecraft:medium_amethyst_bud":1,"minecraft:amethyst_cluster":3,"minecraft:purpur_stairs":1,"minecraft:torch":20,"minecraft:blast_furnace":7,"minecraft:calcite":1,"minecraft:melon":63,"minecraft:dead_bush":8,"minecraft:cobblestone":25,"minecraft:grindstone":1,"minecraft:sugar_cane":213,"minecraft:oak_planks":4,"minecraft:iron_door":10,"minecraft:wall_torch":13,"minecraft:amethyst_block":3,"minecraft:birch_sapling":6,"minecraft:pink_petals":36,"minecraft:nether_wart_block":46,"minecraft:birch_log":757,"minecraft:wheat":530,"minecraft:purpur_block":8,"minecraft:pumpkin_stem":4,"minecraft:light_gray_wool":1,"minecraft:stone_brick_stairs":2,"minecraft:grass":236,"minecraft:oak_log":7,"minecraft:beetroots":151,"minecraft:birch_button":2,"minecraft:dirt":147,"minecraft:netherrack":511,"minecraft:polished_deepslate_wall":6,"minecraft:oak_leaves":4,"minecraft:deepslate":193,"minecraft:nether_gold_ore":7,"minecraft:tuff":10,"minecraft:deepslate_diamond_ore":50,"minecraft:oak_door":2,"minecraft:cherry_sapling":1,"minecraft:stripped_cherry_log":1,"minecraft:stripped_birch_log":1,"minecraft:end_stone":225,"minecraft:glow_lichen":8,"minecraft:nether_bricks":3,"minecraft:ladder":1,"minecraft:cobbled_deepslate_slab":18,"minecraft:weeping_vines":1,"minecraft:birch_slab":7,"minecraft:spruce_leaves":8,"minecraft:cartography_table":1,"minecraft:hay_block":21,"minecraft:redstone_ore":21,"minecraft:furnace":20,"minecraft:carrots":170,"minecraft:andesite":13,"minecraft:gold_block":1,"minecraft:polished_deepslate":2,"minecraft:potatoes":112,"minecraft:deepslate_iron_ore":100,"minecraft:cobblestone_slab":1,"minecraft:lantern":30,"minecraft:packed_ice":47,"minecraft:chorus_plant":22,"minecraft:stone":314,"minecraft:white_wool":1,"minecraft:birch_stairs":37,"minecraft:soul_sand":32,"minecraft:infested_stone_bricks":2,"minecraft:basalt":146,"minecraft:spruce_door":6,"minecraft:cobbled_deepslate_wall":2,"minecraft:oak_fence":2,"minecraft:crafting_table":8,"minecraft:purpur_pillar":16,"minecraft:campfire":2,"minecraft:copper_ore":3,"minecraft:tall_grass":5,"minecraft:deepslate_gold_ore":76,"minecraft:lapis_ore":12,"minecraft:diorite":6,"minecraft:spruce_stairs":1,"minecraft:gray_wool":1,"minecraft:light_blue_bed":3,"minecraft:cobblestone_wall":2,"minecraft:sweet_berry_bush":10,"minecraft:ice":18,"minecraft:white_carpet":3,"minecraft:birch_leaves":233,"minecraft:white_wall_banner":1,"minecraft:coal_ore":240,"minecraft:end_rod":27,"minecraft:cherry_leaves":5,"minecraft:gravel":4,"minecraft:dripstone_block":3,"minecraft:cobweb":23,"minecraft:cracked_stone_bricks":11,"minecraft:spruce_fence_gate":1,"minecraft:stone_bricks":31,"minecraft:mossy_stone_bricks":14,"minecraft:gold_ore":17},"minecraft:broken":{"minecraft:golden_sword":1,"minecraft:stone_hoe":1,"minecraft:shield":2,"minecraft:iron_axe":3,"minecraft:iron_pickaxe":5,"minecraft:wooden_hoe":1},"minecraft:killed_by":{"minecraft:piglin":1,"minecraft:blaze":1,"minecraft:zombie":1,"minecraft:player":5,"minecraft:enderman":2,"minecraft:ender_dragon":1,"minecraft:shulker":2,"minecraft:hoglin":1,"minecraft:skeleton":3},"minecraft:killed":{"minecraft:cave_spider":6,"minecraft:zombified_piglin":2,"minecraft:witch":1,"minecraft:spider":19,"minecraft:shulker":13,"minecraft:skeleton":27,"minecraft:chicken":41,"minecraft:silverfish":7,"minecraft:magma_cube":4,"minecraft:piglin":2,"minecraft:pig":14,"minecraft:zombie_villager":1,"minecraft:creeper":13,"minecraft:sheep":46,"minecraft:trader_llama":4,"minecraft:pillager":3,"minecraft:donkey":1,"minecraft:zombie":71,"minecraft:blaze":3,"minecraft:cow":69,"minecraft:phantom":1,"minecraft:horse":1,"minecraft:bat":1,"minecraft:wandering_trader":1,"minecraft:frog":1,"minecraft:hoglin":1,"minecraft:polar_bear":3,"minecraft:wither_skeleton":1,"minecraft:player":1,"minecraft:enderman":29},"minecraft:dropped":{"minecraft:birch_planks":5,"minecraft:brown_mushroom":3,"minecraft:oak_pressure_plate":2,"minecraft:cooked_beef":28,"minecraft:golden_pickaxe":2,"minecraft:cooked_porkchop":66,"minecraft:iron_horse_armor":2,"minecraft:cracked_stone_bricks":1,"minecraft:birch_slab":1,"minecraft:dirt":7,"minecraft:pumpkin_pie":6,"minecraft:iron_pickaxe":8,"minecraft:dark_oak_planks":1,"minecraft:birch_log":76,"minecraft:gold_ingot":3,"minecraft:oak_door":1,"minecraft:gravel":3,"minecraft:stone_axe":2,"minecraft:blackstone":11,"minecraft:cobbled_deepslate":128,"minecraft:wheat":45,"minecraft:end_stone":115,"minecraft:cooked_mutton":17,"minecraft:charcoal":4,"minecraft:ladder":38,"minecraft:basalt":145,"minecraft:stone_brick_stairs":2,"minecraft:netherrack":778,"minecraft:egg":3,"minecraft:stone_hoe":1,"minecraft:water_bucket":1,"minecraft:golden_boots":1,"minecraft:bread":2,"minecraft:oak_slab":1,"minecraft:wheat_seeds":460,"minecraft:feather":12,"minecraft:cobblestone":84,"minecraft:iron_helmet":4,"minecraft:spruce_stairs":2,"minecraft:coal":2,"minecraft:iron_leggings":1,"minecraft:iron_axe":1,"minecraft:polished_deepslate_wall":6,"minecraft:spruce_sapling":1,"minecraft:beetroot_soup":2,"minecraft:stone_sword":1,"minecraft:raw_copper":9,"minecraft:raw_iron":36,"minecraft:iron_boots":1,"minecraft:nether_bricks":3,"minecraft:ender_eye":1,"minecraft:filled_map":2,"minecraft:shield":2,"minecraft:dragon_egg":1,"minecraft:spruce_planks":18,"minecraft:diamond_pickaxe":1,"minecraft:iron_chestplate":1,"minecraft:andesite":11,"minecraft:carved_pumpkin":1,"minecraft:stone_bricks":4,"minecraft:spider_eye":1,"minecraft:wooden_pickaxe":1,"minecraft:stone_pickaxe":1,"minecraft:magma_block":4,"minecraft:light_blue_bed":1},"minecraft:picked_up":{"minecraft:shulker_shell":12,"minecraft:iron_chestplate":16,"minecraft:wheat":473,"minecraft:nether_brick_fence":2,"minecraft:flower_pot":2,"minecraft:lead":19,"minecraft:birch_button":2,"minecraft:stone_brick_stairs":2,"minecraft:golden_sword":1,"minecraft:brewing_stand":3,"minecraft:polished_deepslate_wall":6,"minecraft:amethyst_block":6,"minecraft:polished_deepslate":2,"minecraft:string":54,"minecraft:raw_copper":36,"minecraft:beetroot_soup":2,"minecraft:iron_leggings":21,"minecraft:beetroot":125,"minecraft:gold_nugget":34,"minecraft:cobbled_deepslate":385,"minecraft:bucket":12,"minecraft:ender_eye":2,"minecraft:cobblestone_slab":1,"minecraft:calcite":1,"minecraft:iron_pickaxe":32,"minecraft:melon_slice":287,"minecraft:iron_boots":19,"minecraft:furnace":22,"minecraft:golden_helmet":1,"minecraft:stick":181,"minecraft:oak_fence":3,"minecraft:torch":177,"minecraft:purpur_pillar":18,"minecraft:porkchop":155,"minecraft:cherry_log":13,"minecraft:pointed_dripstone":10,"minecraft:diorite":6,"minecraft:golden_chestplate":1,"minecraft:cauldron":3,"minecraft:light_gray_bed":26,"minecraft:stone_sword":1,"minecraft:cactus":2,"minecraft:rotten_flesh":124,"minecraft:carved_pumpkin":3,"minecraft:end_rod":60,"minecraft:blaze_rod":2,"minecraft:cod":3,"minecraft:iron_bars":2,"minecraft:cobblestone":428,"minecraft:birch_log":938,"minecraft:pink_petals":516,"minecraft:feather":45,"minecraft:cooked_beef":261,"minecraft:iron_door":10,"minecraft:water_bucket":10,"minecraft:birch_slab":16,"minecraft:andesite":18,"minecraft:golden_leggings":3,"minecraft:potato":374,"minecraft:tuff":9,"minecraft:stripped_birch_log":1,"minecraft:lapis_lazuli":321,"minecraft:dirt":467,"minecraft:lantern":28,"minecraft:bone":85,"minecraft:bow":17,"minecraft:cobbled_deepslate_wall":2,"minecraft:wheat_seeds":1488,"minecraft:raw_gold":146,"minecraft:cobbled_deepslate_slab":20,"minecraft:grindstone":1,"minecraft:mossy_stone_bricks":12,"minecraft:stone_hoe":3,"minecraft:oak_planks":4,"minecraft:cooked_porkchop":344,"minecraft:oak_pressure_plate":10,"minecraft:grass_block":2,"minecraft:spectral_arrow":150,"minecraft:barrel":1,"minecraft:spruce_fence_gate":1,"minecraft:diamond":85,"minecraft:spruce_boat":7,"minecraft:granite":1,"minecraft:end_stone_bricks":3,"minecraft:chorus_fruit":413,"minecraft:charcoal":8,"minecraft:bread":17,"minecraft:oak_sapling":2,"minecraft:netherrack":1346,"minecraft:diamond_pickaxe":4,"minecraft:crafting_table":13,"minecraft:splash_potion":1,"minecraft:chicken":40,"minecraft:ladder":92,"minecraft:golden_pickaxe":1,"minecraft:brown_mushroom":2,"minecraft:gold_block":1,"minecraft:stripped_cherry_log":1,"minecraft:purpur_block":11,"minecraft:shield":22,"minecraft:red_bed":3,"minecraft:iron_axe":19,"minecraft:white_carpet":3,"minecraft:birch_fence":1,"minecraft:blackstone":61,"minecraft:blue_orchid":54,"minecraft:cracked_stone_bricks":10,"minecraft:cartography_table":1,"minecraft:beef":163,"minecraft:player_head":14,"minecraft:iron_nugget":30,"minecraft:light_gray_wool":11,"minecraft:sugar_cane":393,"minecraft:birch_sapling":206,"minecraft:phantom_membrane":2,"minecraft:egg":205,"minecraft:raw_iron":326,"minecraft:end_stone":270,"minecraft:oak_door":2,"minecraft:carrot":675,"minecraft:redstone":338,"minecraft:light_blue_bed":4,"minecraft:iron_horse_armor":1,"minecraft:dark_oak_planks":1,"minecraft:arrow":123,"minecraft:weeping_vines":22,"minecraft:beetroot_seeds":377,"minecraft:nether_bricks":25,"minecraft:hay_block":21,"minecraft:glow_berries":9,"minecraft:mutton":63,"minecraft:rail":2,"minecraft:white_wool":42,"minecraft:basalt":153,"minecraft:magenta_banner":18,"minecraft:glow_ink_sac":11,"minecraft:leather":89,"minecraft:birch_planks":7,"minecraft:crimson_fungus":1,"minecraft:oak_log":7,"minecraft:gunpowder":12,"minecraft:golden_boots":3,"minecraft:nether_wart_block":45,"minecraft:cobbled_deepslate_stairs":4,"minecraft:cobblestone_wall":2,"minecraft:cobblestone_stairs":1,"minecraft:wooden_hoe":1,"minecraft:white_banner":3,"minecraft:cooked_mutton":115,"minecraft:apple":1,"minecraft:stone_bricks":32,"minecraft:iron_ingot":31,"minecraft:stone_pickaxe":1,"minecraft:cooked_chicken":38,"minecraft:iron_sword":5,"minecraft:soul_sand":32,"minecraft:oak_slab":1,"minecraft:milk_bucket":1,"minecraft:pumpkin":70,"minecraft:sweet_berries":76,"minecraft:quartz":24,"minecraft:spyglass":1,"minecraft:dripstone_block":3,"minecraft:gravel":9,"minecraft:birch_stairs":44,"minecraft:amethyst_shard":24,"minecraft:spruce_sapling":1,"minecraft:blast_furnace":11,"minecraft:white_bed":3,"minecraft:dragon_egg":1,"minecraft:spider_eye":13,"minecraft:spruce_door":6,"minecraft:pumpkin_seeds":18,"minecraft:slime_ball":1,"minecraft:stone_axe":2,"minecraft:iron_helmet":26,"minecraft:diamond_axe":5,"minecraft:birch_sign":1,"minecraft:cherry_sapling":3,"minecraft:gray_wool":3,"minecraft:baked_potato":184,"minecraft:melon_seeds":6,"minecraft:coal":305,"minecraft:ender_pearl":24},"minecraft:used":{"minecraft:nether_brick_fence":1,"minecraft:cherry_sapling":3,"minecraft:polished_deepslate":2,"minecraft:ladder":26,"minecraft:chest":2,"minecraft:shield":268,"minecraft:iron_sword":138,"minecraft:player_head":15,"minecraft:rotten_flesh":8,"minecraft:carrot":245,"minecraft:tuff":5,"minecraft:weeping_vines":7,"minecraft:milk_bucket":3,"minecraft:spruce_boat":6,"minecraft:lava_bucket":10,"minecraft:birch_sapling":180,"minecraft:blue_orchid":25,"minecraft:light_blue_bed":4,"minecraft:golden_sword":6,"minecraft:birch_trapdoor":2,"minecraft:birch_button":4,"minecraft:bow":25,"minecraft:hay_block":8,"minecraft:sweet_berries":72,"minecraft:furnace":9,"minecraft:oak_sapling":2,"minecraft:beetroot_seeds":169,"minecraft:egg":76,"minecraft:potato":142,"minecraft:end_stone_bricks":3,"minecraft:diorite":3,"minecraft:spruce_door":6,"minecraft:chorus_fruit":37,"minecraft:stone_pickaxe":92,"minecraft:oak_planks":3,"minecraft:blackstone":1,"minecraft:ender_pearl":9,"minecraft:wooden_pickaxe":38,"minecraft:diamond_axe":801,"minecraft:sugar_cane":87,"minecraft:purpur_pillar":14,"minecraft:white_wool":7,"minecraft:blast_furnace":11,"minecraft:dripstone_block":3,"minecraft:shears":1,"minecraft:end_stone":100,"minecraft:cobbled_deepslate_stairs":4,"minecraft:pumpkin_seeds":17,"minecraft:birch_fence":2,"minecraft:bread":8,"minecraft:birch_slab":23,"minecraft:melon_slice":69,"minecraft:string":1,"minecraft:oak_pressure_plate":5,"minecraft:gravel":5,"minecraft:nether_wart_block":45,"minecraft:fire_charge":1,"minecraft:birch_log":211,"minecraft:andesite":1,"minecraft:purpur_block":5,"minecraft:tropical_fish_bucket":2,"minecraft:bone_meal":9,"minecraft:golden_pickaxe":27,"minecraft:oak_fence":4,"minecraft:stone_sword":7,"minecraft:stone_hoe":157,"minecraft:cooked_chicken":2,"minecraft:netherrack":223,"minecraft:torch":657,"minecraft:brewing_stand":1,"minecraft:dirt":467,"minecraft:spyglass":91,"minecraft:white_carpet":3,"minecraft:cobblestone_wall":2,"minecraft:granite":1,"minecraft:shroomlight":1,"minecraft:birch_door":3,"minecraft:iron_hoe":44,"minecraft:iron_axe":827,"minecraft:polished_deepslate_wall":6,"minecraft:melon_seeds":13,"minecraft:barrel":5,"minecraft:light_gray_wool":2,"minecraft:basalt":4,"minecraft:pumpkin":1,"minecraft:cooked_beef":39,"minecraft:cobbled_deepslate":392,"minecraft:cherry_log":4,"minecraft:light_gray_bed":1,"minecraft:beetroot_soup":1,"minecraft:pointed_dripstone":9,"minecraft:cobbled_deepslate_wall":2,"minecraft:calcite":1,"minecraft:wheat_seeds":612,"minecraft:cooked_mutton":18,"minecraft:water_bucket":290,"minecraft:cobblestone_stairs":1,"minecraft:birch_planks":6,"minecraft:baked_potato":1,"minecraft:spruce_fence_gate":1,"minecraft:cobblestone_slab":1,"minecraft:rail":2,"minecraft:crafting_table":10,"minecraft:red_bed":3,"minecraft:birch_sign":2,"minecraft:spider_eye":2,"minecraft:cod":2,"minecraft:campfire":8,"minecraft:white_bed":5,"minecraft:cake":7,"minecraft:oak_log":1,"minecraft:ender_eye":1,"minecraft:wooden_hoe":59,"minecraft:flower_pot":2,"minecraft:diamond_pickaxe":80,"minecraft:apple":1,"minecraft:iron_pickaxe":2410,"minecraft:stone_axe":86,"minecraft:pink_petals":516,"minecraft:crimson_fungus":1,"minecraft:cobblestone":184,"minecraft:cobbled_deepslate_slab":76,"minecraft:white_banner":3,"minecraft:bucket":302,"minecraft:cooked_porkchop":42,"minecraft:gray_wool":2,"minecraft:splash_potion":1,"minecraft:birch_stairs":50},"minecraft:custom":{"minecraft:animals_bred":34,"minecraft:interact_with_crafting_table":173,"minecraft:open_barrel":334,"minecraft:bell_ring":12,"minecraft:eat_cake_slice":47,"minecraft:leave_game":9,"minecraft:time_since_death":34645,"minecraft:sprint_one_cm":2402939,"minecraft:damage_blocked_by_shield":17120,"minecraft:drop":288,"minecraft:talked_to_villager":11,"minecraft:play_time":1327953,"minecraft:deaths":19,"minecraft:jump":16930,"minecraft:interact_with_brewingstand":3,"minecraft:walk_on_water_one_cm":200363,"minecraft:interact_with_furnace":127,"minecraft:interact_with_cartography_table":1,"minecraft:sleep_in_bed":41,"minecraft:open_enderchest":9,"minecraft:damage_dealt":59735,"minecraft:crouch_one_cm":239669,"minecraft:interact_with_smoker":1,"minecraft:horse_one_cm":1290204,"minecraft:interact_with_smithing_table":1,"minecraft:interact_with_anvil":4,"minecraft:mob_kills":398,"minecraft:interact_with_campfire":641,"minecraft:climb_one_cm":46571,"minecraft:walk_one_cm":4234172,"minecraft:sneak_time":96559,"minecraft:walk_under_water_one_cm":140517,"minecraft:boat_one_cm":65812,"minecraft:interact_with_blast_furnace":52,"minecraft:total_world_time":1327953,"minecraft:pot_flower":2,"minecraft:interact_with_grindstone":1,"minecraft:time_since_rest":34673,"minecraft:damage_taken":15140,"minecraft:swim_one_cm":88035,"minecraft:fly_one_cm":4592352,"minecraft:open_chest":1696,"minecraft:fall_one_cm":320704},"minecraft:crafted":{"minecraft:smooth_stone":21,"minecraft:oak_planks":24,"minecraft:barrel":3,"minecraft:polished_deepslate_wall":6,"minecraft:birch_slab":42,"minecraft:stone":34,"minecraft:warped_planks":4,"minecraft:cake":7,"minecraft:quartz_block":72,"minecraft:bow":2,"minecraft:iron_boots":6,"minecraft:melon_seeds":3,"minecraft:chest":1,"minecraft:birch_door":3,"minecraft:birch_button":1,"minecraft:stone_hoe":2,"minecraft:golden_boots":1,"minecraft:diamond_axe":1,"minecraft:crafting_table":3,"minecraft:wooden_pickaxe":1,"minecraft:iron_helmet":6,"minecraft:cobbled_deepslate_wall":6,"minecraft:copper_ingot":8,"minecraft:hay_block":4,"minecraft:birch_planks":432,"minecraft:pumpkin_seeds":4,"minecraft:campfire":8,"minecraft:light_gray_bed":5,"minecraft:wooden_hoe":1,"minecraft:iron_chestplate":6,"minecraft:diamond_pickaxe":1,"minecraft:shield":11,"minecraft:stick":304,"minecraft:light_blue_dye":3,"minecraft:leather_chestplate":1,"minecraft:iron_ingot":233,"minecraft:iron_pickaxe":9,"minecraft:light_blue_bed":1,"minecraft:gold_ingot":3,"minecraft:birch_stairs":24,"minecraft:beetroot_soup":6,"minecraft:cherry_planks":4,"minecraft:cobbled_deepslate_slab":66,"minecraft:spyglass":1,"minecraft:furnace":7,"minecraft:blast_furnace":4,"minecraft:bone_meal":162,"minecraft:iron_axe":7,"minecraft:ladder":63,"minecraft:iron_hoe":1,"minecraft:stone_pickaxe":1,"minecraft:cobbled_deepslate_stairs":8,"minecraft:redstone_block":4,"minecraft:wheat":153,"minecraft:sugar":81,"minecraft:bone_block":17,"minecraft:crimson_planks":4,"minecraft:iron_sword":1,"minecraft:bowl":4,"minecraft:light_blue_wool":3,"minecraft:leather_helmet":1,"minecraft:bucket":5,"minecraft:stone_axe":1,"minecraft:air":0,"minecraft:bread":1,"minecraft:white_wool":3,"minecraft:birch_trapdoor":2,"minecraft:iron_leggings":5,"minecraft:white_bed":2,"minecraft:pumpkin_pie":47,"minecraft:torch":570}},"DataVersion":3578}